LICENSE
MANIFEST.in
README.rst
setup.py
django_ohm2_pushes_light.egg-info/PKG-INFO
django_ohm2_pushes_light.egg-info/SOURCES.txt
django_ohm2_pushes_light.egg-info/dependency_links.txt
django_ohm2_pushes_light.egg-info/requires.txt
django_ohm2_pushes_light.egg-info/top_level.txt
docs/INFO.txt
ohm2_pushes_light/__init__.py
ohm2_pushes_light/admin.py
ohm2_pushes_light/apps.py
ohm2_pushes_light/context_processors.py
ohm2_pushes_light/decorators.py
ohm2_pushes_light/definitions.py
ohm2_pushes_light/dispatcher.py
ohm2_pushes_light/errors.py
ohm2_pushes_light/managers.py
ohm2_pushes_light/middlewares.py
ohm2_pushes_light/models.py
ohm2_pushes_light/serializers.py
ohm2_pushes_light/settings.py
ohm2_pushes_light/tests.py
ohm2_pushes_light/urls.py
ohm2_pushes_light/utils.py
ohm2_pushes_light/views.py
ohm2_pushes_light/api/.DS_Store
ohm2_pushes_light/api/v1/dispatcher.py
ohm2_pushes_light/api/v1/errors.py
ohm2_pushes_light/api/v1/settings.py
ohm2_pushes_light/api/v1/urls.py
ohm2_pushes_light/api/v1/views.py
ohm2_pushes_light/api/v1/__pycache__/dispatcher.cpython-35.pyc
ohm2_pushes_light/api/v1/__pycache__/errors.cpython-35.pyc
ohm2_pushes_light/api/v1/__pycache__/settings.cpython-35.pyc
ohm2_pushes_light/api/v1/__pycache__/urls.cpython-35.pyc
ohm2_pushes_light/api/v1/__pycache__/views.cpython-35.pyc
ohm2_pushes_light/gateways/firebase/__init__.py
ohm2_pushes_light/gateways/firebase/admin.py
ohm2_pushes_light/gateways/firebase/apps.py
ohm2_pushes_light/gateways/firebase/context_processors.py
ohm2_pushes_light/gateways/firebase/decorators.py
ohm2_pushes_light/gateways/firebase/definitions.py
ohm2_pushes_light/gateways/firebase/dispatcher.py
ohm2_pushes_light/gateways/firebase/errors.py
ohm2_pushes_light/gateways/firebase/managers.py
ohm2_pushes_light/gateways/firebase/middlewares.py
ohm2_pushes_light/gateways/firebase/models.py
ohm2_pushes_light/gateways/firebase/serializers.py
ohm2_pushes_light/gateways/firebase/settings.py
ohm2_pushes_light/gateways/firebase/tests.py
ohm2_pushes_light/gateways/firebase/urls.py
ohm2_pushes_light/gateways/firebase/utils.py
ohm2_pushes_light/gateways/firebase/views.py
ohm2_pushes_light/gateways/firebase/__pycache__/__init__.cpython-35.pyc
